{
  "chapter": 4,
  "title": "제4장. 수식·접속과 문장 구조",
  "questions": [
    {
      "year": 2017,
      "number": 13,
      "text": "다음 예문이 가지고 있는 문제를 지적한 것으로 적절하지 않은 것은? 편안하고 즐겁고 인간다운 생활을 영위하지 못하는 것은 생활 쓰레기를 늘리고 쓰레기 분리도 철저히 하지 않고 밤에 몰래 폐수를 갖다 버리고 이를 눈감아 준 개인과 기업 및 공무원들의 용서할 수 없는 비양심적인 행동 때문이다.",
      "choice_1": "문장의 길이가 너무 길다.",
      "choice_2": "수식 관계가 분명하지 않다.",
      "choice_3": "조사와 어미의 쓰임이 정확하지 않다.",
      "choice_4": "내포 및 접속 관계가 너무 복잡하다.",
      "answer": "3",
      "explanation": "제시된 예문은 문장의 길이가 지나치게 길고 수식 관계가 불분명하며 내포 및 접속 관계가 복잡하여 전체적인 의미 파악이 어렵다는 문제점을 가지고 있습니다. 그러나 조사나 어미의 쓰임에서 문법적인 오류는 발견되지 않으므로, '조사와 어미의 쓰임이 정확하지 않다'는 지적은 적절하지 않습니다."
    },
    {
      "year": 2017,
      "number": 14,
      "text": "다음 중 구조적 중의성을 보이고 있는 문장은?",
      "choice_1": "제가 희망하는 직장은 초등학교 교사입니다.",
      "choice_2": "바이러스는 보통의 현미경으로는 볼 수 없다.",
      "choice_3": "아름다운 새들의 노래 소리가 들려온다.",
      "choice_4": "인구가 많은 도시에서는 재미있는 일도 많이 일어난다.",
      "answer": "3",
      "explanation": "문장 ③은 '아름다운'이라는 수식어가 '새들'을 꾸미는지, 아니면 '새들의 노래 소리' 전체를 꾸미는지에 따라 의미가 달라진다. '아름다운 새들'의 노래 소리라는 의미일 수도 있고, '새들이 부르는 아름다운 노래 소리'라는 의미일 수도 있으므로 구조적 중의성을 가진다."
    },
    {
      "year": 2017,
      "number": 15,
      "text": "다음 중 수식의 관점에서 가장 자연스러운 문장은?",
      "choice_1": "그 사건 이후로 우리의 사회에 대한 관심은 더욱 높아져 갔다.",
      "choice_2": "방음벽이 파손되더라도 방음판의 비산 등으로 2차 피해가 없어야 한다.",
      "choice_3": "저희 직원들은 편안한 여러분의 주거 생활을 위해 최선을 다하겠습니다.",
      "choice_4": "우리가 바라는 것은 오로지 이 땅에서 자유롭고 평화롭게 사는 것입니다.",
      "answer": "4",
      "explanation": "문장 ④는 각 수식어가 꾸미는 대상과 의미 연결이 명확하여 수식의 관점에서 가장 자연스러운 문장입니다. '우리가 바라는 것', '이 땅에서 자유롭고 평화롭게 사는 것'처럼 모든 요소가 어색함 없이 배열되어 의미 전달이 명확합니다."
    },
    {
      "year": 2017,
      "number": 16,
      "text": "다음 중 접속의 관점에서 가장 자연스러운 문장은?",
      "choice_1": "인간은 자연을 지배하기도 하고 자연에 복종하기도 한다.",
      "choice_2": "정부는 사고 원인 파악과 재발 방지 대책을 조속히 수립하겠다고 밝혔다.",
      "choice_3": "높은 산을 잘라 내 직선으로 뚫리고 있는 도로 공사 현장입니다.",
      "choice_4": "허준은 우리에게 널리 알려진 인물로서 영화로도 많이 만들어졌다.",
      "answer": "1",
      "explanation": "보기 ①은 'V-기도 하고 V-기도 하다' 구문을 사용하여 한 주체의 상반되거나 대등한 두 가지 행동이나 상태를 자연스럽게 연결하고 있습니다. '인간'이 '자연을 지배하는' 행동과 '자연에 복종하는' 행동이라는 양면적인 모습을 유기적으로 접속하여 제시하고 있어 가장 자연스러운 문장으로 평가할 수 있습니다."
    },
    {
      "year": 2017,
      "number": 17,
      "text": "다음 중 접속의 관점에서 가장 자연스럽지 않은 문장은?",
      "choice_1": "개인은 사회를 발전시키기도 하고 사회의 발전을 저해하기도 하면서 살아 왔다.",
      "choice_2": "민주적인 의사 결정의 번복 또는 평등의 원칙에 반하는 행위는 민주 사회의 질서를 훼손하는 것이다.",
      "choice_3": "공격진에선 설기현이 중앙을, 스피드가 뛰어난 이천수와 차두리가 왼쪽과 오른쪽을 맡았다.",
      "choice_4": "대학은 모든 시대와 나라에서 형성된 가장 심오한 진리를 탐구하고 치밀한 과학적 정신을 배양ㆍ형성하는 도량입니다.",
      "answer": "2",
      "explanation": "②번 문장은 '민주적인 의사 결정의 번복 또는 평등의 원칙에 반하는 행위'에서 '또는'으로 연결된 두 요소의 형태가 비대칭적이어서 접속이 가장 부자연스럽습니다. '번복'은 명사형이지만, 뒤의 '평등의 원칙에 반하는 행위'는 '행위'를 포함하는 구의 형태를 띠고 있습니다. 접속되는 두 요소의 문법적 형태를 유사하게 맞추는 것이 자연스러운 연결을 만듭니다. 예를 들어, '민주적인 의사 결정을 번복하는 행위 또는 평등의 원칙에 반하는 행위'와 같이 구성해야 더 자연스럽습니다."
    },
    {
      "year": 2018,
      "number": 12,
      "text": "다음 중 수식의 관점에서 자연스럽지 않은 문장은?",
      "choice_1": "이 프로그램은 바이러스 제거는 물론, 데이터를 원상태로 복구까지 해 준다.",
      "choice_2": "우리가 바라는 것은 이 땅에서 자유롭고 평화롭게 사는 것입니다.",
      "choice_3": "당당하게 아내는 아이를 낳기 위해 결혼한 것이 아니라고 주장했다.",
      "choice_4": "며칠 동안 약물 치료를 한 후에도 차도가 없으면 종합병원으로 가십시오.",
      "answer": "3",
      "explanation": "③번 문장은 '당당하게'라는 부사의 위치가 부자연스러워 의미 전달이 매끄럽지 않습니다. '당당하게'는 '주장했다'를 수식해야 하는데, 문장 구조상 '아내는'을 수식하는 것처럼 보이거나 문장 전체의 의미를 모호하게 만듭니다. '아내는 당당하게 아이를 낳기 위해 결혼한 것이 아니라고 주장했다' 또는 '아내는 아이를 낳기 위해 결혼한 것이 아니라고 당당하게 주장했다'와 같이 부사의 위치를 옮겨야 자연스러운 문장이 됩니다."
    },
    {
      "year": 2018,
      "number": 13,
      "text": "다음 중 수식의 관점에서 밑줄 친 부분이 가장 자연스러운 문장은?",
      "choice_1": "그 사건 이후로 사회에 대한 우리의 관심은 더욱 높아져 갔다.",
      "choice_2": "편안한 여러분의 주거 생활을 위해 최선을 다하겠습니다.",
      "choice_3": "저는 20세의 명문대에 재학 중인 신체 건강한 남자입니다.",
      "choice_4": "미국은 법률을 제정하여 연령을 이유로 고용, 해고, 근로 조건 등에서 차별 대우를 금지하고 있다.",
      "answer": "1",
      "explanation": "문장의 수식 관계는 의미 전달의 명확성과 자연스러움에 큰 영향을 미칩니다. 정답인 ①번 문장은 '사회에 대한 우리의 관심', '더욱 높아져 갔다'와 같이 수식어가 피수식어를 자연스럽게 꾸며주어 의미가 명확하게 전달됩니다."
    },
    {
      "year": 2018,
      "number": 14,
      "text": "다음 중 접속의 관점에서 가장 자연스러운 문장은?",
      "choice_1": "개인은 사회를 발전시키기도 하고 저해하기도 하면서 살아왔다.",
      "choice_2": "그동안 박 감독은 좋은 성적을 거두었을 뿐만 아니라 우수한 선수도 많이 발굴했다.",
      "choice_3": "등기 신청은 소유자 본인이 직접 또는 법무사에게 위임할 수 있다.",
      "choice_4": "허준은 우리에게 널리 알려진 인물로서 영화로도 많이 만들어졌다.",
      "answer": "2",
      "explanation": "② '을 뿐만 아니라 ~도'는 앞 내용에 뒤의 내용을 덧붙여 나타낼 때 쓰는 연결 어미입니다. '박 감독이 좋은 성적을 거둔 것'과 '우수한 선수를 많이 발굴한 것'은 모두 박 감독의 긍정적인 성과를 나열하는 것으로, 가장 자연스러운 접속입니다."
    },
    {
      "year": 2018,
      "number": 15,
      "text": "다음 중 접속의 관점에서 자연스럽지 않은 문장은?",
      "choice_1": "정부는 사고 원인을 파악하여 재발 방지 대책을 조속히 수립하겠다고 밝혔다.",
      "choice_2": "소생의 자식 결혼 시에 축복과 격려를 해 주신 데 대하여 감사를 드립니다.",
      "choice_3": "작가의 독창성은 학교에서 배우는 공식화된 가르침을 그대로 적용하는 데서 가능한 것이 아니고 자신의 노력으로 자기의 화법에 맞는 기법을 만들어 내는 데서 가능한 것이다.",
      "choice_4": "민주적인 의사 결정의 번복 또는 평등의 원칙에 반하는 행위는 민주적인 사회 질서를 훼손하는 행위이다.",
      "answer": "4",
      "explanation": "④번 문장은 '민주적인 의사 결정의 번복 또는 평등의 원칙에 반하는 행위는 민주적인 사회 질서를 훼손하는 행위이다.'로, '번복'과 '평등의 원칙에 반하는 행위'를 '또는'으로 연결하여 '훼손하는 행위'의 주어로 삼고 있습니다. 이때 '번복'은 명사이며 '평등의 원칙에 반하는 행위'는 '행위'라는 명사구를 포함하고 있어 문장 내에서 동등한 지위의 요소를 연결하기에는 접속의 관점에서 자연스럽지 않습니다. '번복' 또한 '행위'임을 명확히 하기 위해 '민주적인 의사 결정의 번복 행위 또는 평등의 원칙에 반하는 행위는'처럼 '행위'를 넣어 병렬 구조를 맞추거나, '민주적인 의사 결정의 번복과 평등의 원칙에 반하는 행위는'과 같이 연결하는 것이 접속의 관점에서 더 자연스럽습니다."
    },
    {
      "year": 2019,
      "number": 13,
      "text": "다음 중 수식의 관점에서 봤을 때 가장 자연스러운 문장은?",
      "choice_1": "저는 20세의 명문대에 재학 중인 신체 건강한 남자입니다.",
      "choice_2": "그 사건 이후로 우리의 사회에 대한 관심은 더욱 높아져 갔다.",
      "choice_3": "옹진군에는 진주와 같이 아름답고 영롱한 100개의 섬들이 있다.",
      "choice_4": "바이러스 제거는 물론 원상태로 데이터 복구까지 해 준다.",
      "answer": "3",
      "explanation": "정답 ③번 문장은 '진주와 같이 아름답고 영롱한'이라는 비유적 표현이 '100개의 섬들'을 자연스럽고 풍성하게 수식하고 있습니다. '진주와 같이'가 '아름답고 영롱한'이라는 형용사구를 효과적으로 강화하며 전체적으로 수식 관계가 매끄럽습니다."
    },
    {
      "year": 2019,
      "number": 14,
      "text": "다음 중 잘못된 수식 구성이 포함된 문장은?",
      "choice_1": "소설가와 영화감독이 호흡을 맞추면 영화를 상품으로 만드는 데 성공할 확률이 얼마나 될까?",
      "choice_2": "미국은 법을 제정하여 연령을 이유로 고용, 해고, 근로 조건 등에서 차별 대우를 금지하고 있다.",
      "choice_3": "우리가 바라는 것은 이 땅에서 자유롭고 평화롭게 사는 것입니다.",
      "choice_4": "물질 특허를 둘러싼 시비는 제약업계와 같은 정밀화학산업에서 자주 일어난다.",
      "answer": "2",
      "explanation": "정답은 ②입니다. 문장 ②에서 '연령을 이유로'와 '고용, 해고, 근로 조건 등에서'는 '차별 대우'라는 명사를 수식하는 것이 자연스럽습니다. 그러나 현재 문장에서는 이들이 '차별 대우를 금지하고 있다' 전체를 수식하는 부사어처럼 배열되어 있어 의미 연결이 다소 어색하고 모호해집니다. '연령을 이유로 한 차별 대우'나 '고용, 해고, 근로 조건 등에서 이루어지는 차별 대우'와 같이 '차별 대우'를 직접 수식하도록 구성하는 것이 더 명확하고 자연스러운 표현입니다. 따라서 잘못된 수식 구성이 포함된 문장으로 볼 수 있습니다."
    },
    {
      "year": 2019,
      "number": 15,
      "text": "다음 중 접속의 관점에서 가장 자연스러운 문장은?",
      "choice_1": "등기 신청은 소유자 본인이 직접 하거나 법무사에게 위임할 수 있다.",
      "choice_2": "인간은 자연을 지배하기도 하고 복종하기도 한다.",
      "choice_3": "풍토병에 걸리지 않으려면 물과 음식은 반드시 익혀 먹어야 한다.",
      "choice_4": "이 난로는 그을음과 열효율을 높이기 위해 최근에 새로 개발된 것이다.",
      "answer": "1",
      "explanation": "정답은 ①번이다. 문장 ①은 등기 신청의 두 가지 방식을 '직접 하거나 법무사에게 위임할 수 있다'와 같이 '-거나'라는 접속 어미를 사용하여 명확하고 논리적으로 연결하고 있다. 두 선택지는 대등하며 어떠한 의미적, 논리적 모순도 없이 자연스러운 접속을 보여주므로 가장 자연스러운 문장이다."
    },
    {
      "year": 2019,
      "number": 16,
      "text": "다음 중 접속의 관점에서 밑줄 친 부분이 자연스럽지 않은 문장은?",
      "choice_1": "이곳은 높은 산을 잘라 내 직선으로 뚫고 있는 도로 공사 현장입니다.",
      "choice_2": "같은 대상을 다르게 표기하거나 표기를 잘못하여 외국인의 불편을 초래하는 것을 예방해야 한다.",
      "choice_3": "여기에 대한 개념과 논평을 한다는 것은 방대한 양이 되기 때문에 다음 기회로 넘기겠습니다.",
      "choice_4": "공격진에서는 손흥민 선수가 중앙을, 스피드가 뛰어난 이승우와 황희찬 선수가 왼쪽과 오른쪽 날개를 맡을 예정이다.",
      "answer": "3",
      "explanation": "문장 ③은 '개념과 논평을 한다는 것'은 '개념을 설명하고 논평하는 행위'를 의미하는데, '행위' 그 자체가 '방대한 양이 된다'고 표현하는 것은 어색합니다. 문맥상 '개념과 논평의 내용'이 방대하여 설명하기 어렵다는 의미이므로, '여기에 대한 개념과 논평은 내용이 방대하기 때문에' 또는 '여기에 대해 개념을 설명하고 논평하는 것이 방대하기 때문에'와 같이 표현하는 것이 자연스럽습니다. 현재의 문장은 서술어가 지칭하는 대상과의 접속이 어색하여 부자연스럽습니다."
    }
  ]
}