{
  "chapter": 2,
  "title": "제2장. 쌀의 성분과 품질",
  "questions": [
    {
      "year": 2013,
      "number": 2,
      "text": "쌀을 구성하는 성분 가운데 함량이 가장 높은 것은?",
      "choice_1": "단백질",
      "choice_2": "지방",
      "choice_3": "당질",
      "choice_4": "섬유",
      "answer": "3",
      "explanation": "쌀은 전 세계적으로 주식으로 이용되는 중요한 식량 작물이며, 주요 에너지원으로서 당질(탄수화물)의 함량이 가장 높습니다. 쌀의 전체 무게 중 약 75~80%가 당질로 구성되어 있습니다."
    },
    {
      "year": 2013,
      "number": 34,
      "text": "찹쌀이 멥쌀과 다른 점은?",
      "choice_1": "녹말이 아밀로오스뿐이다.",
      "choice_2": "녹말이 아밀로펙틴으로만 구성되어 있다.",
      "choice_3": "아밀로펙틴의 함량이 5∼30% 정도이다.",
      "choice_4": "녹말이 투명하고 말갛다.",
      "answer": "2",
      "explanation": "찹쌀은 녹말을 구성하는 아밀로펙틴의 함량이 거의 100%에 가깝고, 아밀로오스는 거의 함유하고 있지 않습니다. 이러한 특성 때문에 찹쌀은 찰기가 강합니다. 반면 멥쌀은 아밀로오스를 15~30% 정도 함유하고 있어 찹쌀보다 찰기가 적습니다."
    },
    {
      "year": 2013,
      "number": 35,
      "text": "다음 중 혈중 콜레스테롤을 저하시키는 능력이 높은 지방산은?",
      "choice_1": "팔미트산",
      "choice_2": "리놀레산",
      "choice_3": "헥사날",
      "choice_4": "올레산",
      "answer": "2",
      "explanation": "정답은 ② 리놀레산입니다. 리놀레산은 다불포화지방산(polyunsaturated fatty acid, PUFA)의 일종으로, 필수지방산에 해당합니다. 리놀레산은 혈액 내 총 콜레스테롤과 저밀도 지단백(LDL) 콜레스테롤 수치를 효과적으로 낮추는 능력이 뛰어난 것으로 알려져 있습니다. 이는 콜레스테롤 대사에 긍정적인 영향을 미쳐 심혈관 질환 예방에 도움을 줍니다."
    },
    {
      "year": 2014,
      "number": 2,
      "text": "현미를 도정할 때 나타나는 특징으로 바른 것은?",
      "choice_1": "도정할수록 지방 함량이 증가한다.",
      "choice_2": "도정할수록 단백질 함량이 낮아진다.",
      "choice_3": "도정할수록 비타민A 함량이 증가한다.",
      "choice_4": "영양성분의 함량과 도정은 관계가 없다.",
      "answer": "2",
      "explanation": "현미를 도정하여 백미를 만드는 과정에서 쌀의 겉껍질인 미강층과 배아가 제거됩니다. 단백질은 주로 미강층과 배아에 집중되어 있으므로, 이 부분이 제거됨에 따라 단백질 함량이 낮아지게 됩니다."
    },
    {
      "year": 2014,
      "number": 5,
      "text": "벼의 현미에서 쌀겨가 차지하는 비율은?",
      "choice_1": "약 5%",
      "choice_2": "약 10%",
      "choice_3": "약 15%",
      "choice_4": "약 20%",
      "answer": "2",
      "explanation": "현미에서 쌀겨가 차지하는 비율은 품종 및 도정 정도에 따라 다소 차이가 있지만, 일반적으로 현미 중량의 약 5~10%를 차지합니다. 따라서 약 10%는 쌀겨가 차지하는 적절한 비율을 나타냅니다. 쌀겨는 도정 과정에서 분리되어 영양분이 풍부한 부산물로 활용됩니다."
    },
    {
      "year": 2014,
      "number": 6,
      "text": "우리나라에서 단립종에 해당하는 쌀(현미)의 장/폭(길이/너비)비는?",
      "choice_1": "2.0 이하",
      "choice_2": "2.1 ∼ 2.5",
      "choice_3": "2.6 ∼ 3.0",
      "choice_4": "3.1 ∼ 3.5",
      "answer": "1",
      "explanation": "단립종 쌀(현미)은 길이가 짧고 너비가 넓어 전체적으로 둥근 형태를 띠며, 길이에 대한 너비의 비율인 장/폭 비가 2.0 이하인 것이 특징입니다. 우리나라에서 주로 재배되고 소비되는 자포니카형 쌀이 대표적인 단립종에 해당합니다."
    },
    {
      "year": 2014,
      "number": 7,
      "text": "다음 중 5분도 쌀을 설명하는 것은?",
      "choice_1": "현미 중량의 약 90%를 도정한 쌀",
      "choice_2": "현미 중량의 약 93%를 도정한 쌀",
      "choice_3": "현미 중량의 약 95%를 도정한 쌀",
      "choice_4": "현미 중량의 약 97%를 도정한 쌀",
      "answer": "4",
      "explanation": "5분도 쌀은 현미 중량의 약 97%를 도정한 쌀을 말합니다. 이는 현미의 쌀겨층 중 약 절반 정도를 벗겨낸 상태로, 백미에 비해 영양분이 풍부하면서도 부드러운 식감을 가집니다."
    },
    {
      "year": 2015,
      "number": 1,
      "text": "현미의 전분함량은?",
      "choice_1": "70 ~ 75%",
      "choice_2": "75 ~ 80%",
      "choice_3": "80 ~ 85%",
      "choice_4": "85 ~ 90%",
      "answer": "1,2",
      "explanation": "현미의 전분 함량은 품종 및 재배 환경에 따라 다소 차이가 있지만, 일반적으로 70~80% 범위에 해당합니다. 따라서 제시된 보기 중 ① 70~75%와 ② 75~80%는 모두 현미의 일반적인 전분 함량 범위에 포함되는 값으로 볼 수 있습니다."
    },
    {
      "year": 2015,
      "number": 2,
      "text": "쌀 단백질에 대한 설명으로 적합한 것은?",
      "choice_1": "쌀단백질의 아미노산가는 밀가루보다 낮다.",
      "choice_2": "쌀단백질의 소화흡수율은 옥수수보다 낮다.",
      "choice_3": "쌀의 글루텔린에는 필수아미노산인 리신의 함량이 밀가루보다 2배정도 높다.",
      "choice_4": "쌀의 단백질은 글루텔린과 프롤라민이 대부분이며, 프롤라민이 70 ~ 80%를 차지한다.",
      "answer": "3",
      "explanation": "쌀 단백질의 주성분은 글루텔린이며, 글루텔린은 필수아미노산인 리신의 함량이 높아 쌀의 영양학적 가치를 높입니다. 밀가루 단백질과 비교했을 때 쌀의 글루텔린에 함유된 리신은 2배 정도 높으므로 ③번 보기가 적합합니다."
    },
    {
      "year": 2015,
      "number": 3,
      "text": "쌀 함유 성분 중 항산화활성이 높아 식품첨가용 원료 등으로 이용되는 색소는?",
      "choice_1": "토코페롤",
      "choice_2": "오리자놀",
      "choice_3": "아밀로펙틴",
      "choice_4": "안토시아닌",
      "answer": "4",
      "explanation": "안토시아닌은 쌀의 색소 성분 중 하나로, 특히 유색미에 풍부하게 함유되어 있습니다. 강한 항산화 활성을 가지고 있으며, 붉은색, 보라색 등 다양한 색을 띠어 식품의 색상 부여 및 기능성 원료로 활용됩니다."
    },
    {
      "year": 2015,
      "number": 4,
      "text": "알벼에서 왕겨가 차지하는 비중은?",
      "choice_1": "약 5%",
      "choice_2": "약 10%",
      "choice_3": "약 15%",
      "choice_4": "약 20%",
      "answer": "4",
      "explanation": "알벼는 벼에서 수확한 그대로의 껍질이 있는 쌀을 말합니다. 알벼의 구성 성분은 왕겨, 현미, 쌀눈 등으로 나눌 수 있는데, 이 중 왕겨는 알벼 전체 중량의 약 20%를 차지합니다. 왕겨는 벼를 보호하는 역할을 하며, 도정 과정에서 분리되어 사료나 연료 등으로 활용됩니다."
    },
    {
      "year": 2015,
      "number": 5,
      "text": "쌀겨 성분 중 기름이 차지하는 비중은?",
      "choice_1": "약 5%",
      "choice_2": "약 10%",
      "choice_3": "약 15%",
      "choice_4": "약 20%",
      "answer": "4",
      "explanation": "쌀겨(미강)는 벼를 도정하는 과정에서 쌀의 겉껍질인 겨층이 벗겨져 나오는 부산물입니다. 쌀겨의 성분은 수분 약 10~15%, 단백질 약 10~15%, 지방(기름) 약 15~20%, 탄수화물 약 50~60%, 섬유질 약 5~10%, 회분 약 5~10% 등으로 구성됩니다. 이 중 기름(지방)은 약 15~20%를 차지하며, 특히 '쌀겨 기름' 또는 '미강유'라고 불리는 식용유의 원료가 됩니다. 따라서 약 20%가 가장 적합한 설명입니다."
    },
    {
      "year": 2015,
      "number": 7,
      "text": "찹쌀이 멥쌀과 다른 것은?",
      "choice_1": "녹말이 아밀로펙틴뿐이다.",
      "choice_2": "녹말이 아밀로오스뿐이다.",
      "choice_3": "녹말 중에 아밀로펙틴이 5~30%를 차지한다.",
      "choice_4": "녹말 중에 아밀로오스가 5~30%를 차지한다.",
      "answer": "1",
      "explanation": "찹쌀과 멥쌀의 가장 큰 차이는 녹말 구성 성분입니다. 찹쌀의 녹말은 거의 100% 아밀로펙틴으로만 이루어져 있어 끈적한 찰기를 띠는 반면, 멥쌀은 아밀로오스를 약 15~30% 함유하고 있어 찰기가 찹쌀보다 적습니다. 따라서 '녹말이 아밀로펙틴뿐이다'는 찹쌀의 특징이자 멥쌀과의 차이를 명확히 설명하는 내용입니다."
    },
    {
      "year": 2015,
      "number": 8,
      "text": "다음 중 술제조용으로 적합한 쌀은?",
      "choice_1": "소립종의 복백미",
      "choice_2": "대립종의 심백미",
      "choice_3": "소립종의 반사립",
      "choice_4": "대립종의 유백립",
      "answer": "2",
      "explanation": "술을 제조할 때는 쌀알의 중심부에 전분이 집중되어 있고 단백질과 지방 함량이 낮은 품종이 유리합니다. 이러한 특징을 가진 쌀을 심백미(心白米)라고 하며, 심백은 효소 작용이 활발하여 당화 및 발효 효율을 높입니다. 또한, 쌀알이 큰 대립종은 도정 시 전분 손실을 줄이고 심백 부분을 온전히 보존하기에 적합하여 주조용으로 선호됩니다."
    },
    {
      "year": 2015,
      "number": 9,
      "text": "다음 중 5분도 쌀에 대한 것은?",
      "choice_1": "현미 중량의 97%를 도정한 쌀",
      "choice_2": "현미 중량의 95%를 도정한 쌀",
      "choice_3": "현미 중량의 93%를 도정한 쌀",
      "choice_4": "현미 중량의 90%를 도정한 쌀",
      "answer": "1",
      "explanation": "5분도 쌀은 현미에서 쌀겨층의 약 50%를 제거한 쌀을 의미하며, 이는 현미 중량의 약 97%를 도정한 상태입니다. 따라서 ①이 정답입니다."
    },
    {
      "year": 2015,
      "number": 27,
      "text": "쌀에서 Mg/K비와 밥맛의 관계를 잘 설명한 것은?",
      "choice_1": "Mg/K 비가 낮은 쌀이 밥맛이 좋다.",
      "choice_2": "Mg/K 비가 높은 쌀이 밥맛이 좋다.",
      "choice_3": "Mg/K 비가 낮으면 찰기가 높다.",
      "choice_4": "Mg/K 비와 밥맛은 관계가 없다.",
      "answer": "2",
      "explanation": "Mg/K 비는 쌀의 밥맛을 결정하는 중요한 지표 중 하나입니다. 일반적으로 마그네슘(Mg)은 전분과의 복합체를 형성하여 밥의 찰기와 질감을 좋게 하는 데 기여하고, 칼륨(K)은 필수 영양소이지만 특정 비율 이상이 되면 밥맛에 부정적인 영향을 줄 수 있습니다. 따라서 Mg/K 비가 높을수록 전분의 호화 특성이 좋아 밥의 찰기와 윤기가 더 좋으며 부드러운 밥맛을 내는 것으로 알려져 있습니다."
    },
    {
      "year": 2016,
      "number": 2,
      "text": "쌀에 함유된 천연성분 중 색소로 이용하는 것은?",
      "choice_1": "페룰산",
      "choice_2": "리놀레산",
      "choice_3": "안토시아닌",
      "choice_4": "펜타날",
      "answer": "3",
      "explanation": "쌀에 함유된 천연성분 중 색소로 이용되는 대표적인 물질은 안토시아닌입니다. 특히 흑미나 적미와 같은 유색미에는 안토시아닌 색소가 다량 함유되어 있어 쌀의 붉거나 검붉은 색을 나타내며, 식품 색소 및 기능성 성분으로 활용됩니다."
    },
    {
      "year": 2016,
      "number": 3,
      "text": "멥쌀과 찹쌀에 대한 설명으로 바른 것은?",
      "choice_1": "멥쌀은 녹말이 아밀로펙틴뿐이다.",
      "choice_2": "찹쌀은 녹말이 아밀로오스뿐이다.",
      "choice_3": "멥쌀에는 녹말이 아밀로오스가 7∼33% 정도 함유되어 있다.",
      "choice_4": "찹쌀에는 녹말이 아밀로펙틴이 7∼33% 정도 함유되어 있다.",
      "answer": "3",
      "explanation": "멥쌀은 아밀로오스와 아밀로펙틴 두 가지 녹말 성분을 모두 포함하며, 그중 아밀로오스가 7~33% 정도 함유되어 있습니다. 찹쌀은 녹말의 대부분이 아밀로펙틴으로 구성되어 있으며, 아밀로오스는 거의 함유되어 있지 않습니다."
    },
    {
      "year": 2016,
      "number": 5,
      "text": "벼의 도정과정으로 바른 것은?",
      "choice_1": "알벼 → 현백 → 정선 → 제현 → 흰쌀",
      "choice_2": "알벼 → 정선 → 제현 → 현백 → 흰쌀",
      "choice_3": "알벼 → 현백 → 제현 → 정선 → 흰쌀",
      "choice_4": "알벼 → 제현 → 정선 → 현백 → 흰쌀",
      "answer": "2",
      "explanation": "벼의 도정 과정은 수확된 알벼(정조)를 정선하여 이물질을 제거하고, 제현 과정을 통해 왕겨를 벗겨내 현미를 만들며, 마지막으로 현미를 깎아 미강층을 제거하는 현백 과정을 거쳐 흰쌀을 얻는 순서로 진행됩니다. 따라서 '알벼 → 정선 → 제현 → 현백 → 흰쌀'의 순서가 올바릅니다."
    },
    {
      "year": 2016,
      "number": 6,
      "text": "5분도 쌀은 다음 중 무엇인가?",
      "choice_1": "현미 중량의 약 90%로 도정한 쌀",
      "choice_2": "현미 중량의 약 93%로 도정한 쌀",
      "choice_3": "현미 중량의 약 95%로 도정한 쌀",
      "choice_4": "현미 중량의 약 97%로 도정한 쌀",
      "answer": "4",
      "explanation": "5분도 쌀은 현미 중량의 약 97%로 도정한 쌀을 의미합니다. 이는 현미에서 쌀겨층의 약 50% 정도를 제거한 상태의 쌀로, 현미보다 부드럽고 백미보다는 영양소가 더 많이 남아있는 중간 형태의 쌀입니다. 도정 정도는 일반적으로 숫자가 커질수록 쌀겨층 제거율이 높아져 백미에 가까워지지만, 5분도 도정은 현미 중량 대비 97% 수준을 유지하여 쌀눈과 쌀겨층 일부를 보존합니다."
    },
    {
      "year": 2016,
      "number": 20,
      "text": "쌀 배유의 저장물질 가운데 가장 많은 것은?",
      "choice_1": "단백질",
      "choice_2": "지질",
      "choice_3": "녹말",
      "choice_4": "아미노산",
      "answer": "3",
      "explanation": "쌀 배유는 식물의 주요 에너지 저장 기관으로, 대부분 녹말(전분)을 저장합니다. 쌀 배유 건조 중량의 약 70~80%가 녹말입니다. 이는 쌀의 주된 저장 탄수화물로서 발아 시 에너지원으로 사용되며, 사람에게는 주된 에너지원 역할을 합니다."
    },
    {
      "year": 2016,
      "number": 29,
      "text": "현미에서 다음 중 무게비율이 가장 높은 것은?",
      "choice_1": "배",
      "choice_2": "배유",
      "choice_3": "호분층",
      "choice_4": "종피",
      "answer": "2",
      "explanation": "현미는 쌀알의 바깥 부분인 종피와 그 아래 호분층, 배, 그리고 대부분을 차지하는 배유로 구성됩니다. 이 중 배유는 주로 전분을 저장하는 부분으로, 현미 전체 무게의 약 80~90%를 차지하여 무게 비율이 가장 높습니다."
    },
    {
      "year": 2017,
      "number": 2,
      "text": "다음 중 벼의 도정과정으로 바른 것은?",
      "choice_1": "알벼 → 제현 → 정선 → 현백 → 흰쌀",
      "choice_2": "알벼 → 현배 → 정선 → 제현 → 흰쌀",
      "choice_3": "알벼 → 정선 → 제현 → 현백 → 흰쌀",
      "choice_4": "알벼 → 제현 → 현백 → 정선 → 흰쌀",
      "answer": "3",
      "explanation": "벼의 도정 과정은 알벼(수확한 벼)를 먼저 정선(이물질 제거)하고, 이어서 제현(왕겨 제거)하여 현미를 만든 후, 현백(쌀겨 및 배아 제거)하여 백미를 만드는 순서로 진행됩니다. 따라서 정선이 제현보다 먼저 이루어져야 하며, 그 후에 현백 과정이 이어집니다."
    },
    {
      "year": 2017,
      "number": 5,
      "text": "다음 성분들 중 쌀에 가장 많이 들어있는 것은?",
      "choice_1": "당질",
      "choice_2": "단백질",
      "choice_3": "지방",
      "choice_4": "섬유",
      "answer": "1",
      "explanation": "쌀의 주요 성분은 탄수화물로, 전체의 약 70~80%를 차지하며 주된 에너지원입니다."
    },
    {
      "year": 2017,
      "number": 6,
      "text": "현미의 지방에 대한 설명으로 옳은 것은?",
      "choice_1": "쌀 지방의 소화흡수율은 약 50%로 매우 낮다.",
      "choice_2": "쌀에는 리놀레산ㆍ올레산 등의 포화지방산이 70% 이상이다.",
      "choice_3": "올레산은 혈액중의 콜레스테롤을 저하시킨다.",
      "choice_4": "리놀레산은 산소와 결합하여 산패를 유발한다.",
      "answer": "4",
      "explanation": "리놀레산과 같은 불포화지방산은 이중결합을 많이 가지고 있어 산소와 쉽게 반응하며 산패(rancidity)를 유발하는 주요 원인이 됩니다. 현미의 지방은 이러한 불포화지방산 함량이 높아 산패에 취약한 특성을 가집니다."
    },
    {
      "year": 2017,
      "number": 7,
      "text": "다음 중 찌는 떡에 해당하는 것은?",
      "choice_1": "경단, 시루떡",
      "choice_2": "시루떡, 설기",
      "choice_3": "설기, 증편",
      "choice_4": "증편, 시루떡",
      "answer": "2",
      "explanation": "정답은 ②번입니다. 시루떡은 쌀가루를 시루에 켜켜이 안쳐서 찌는 방식으로 만드는 떡이며, 설기 또한 쌀가루를 시루에 넣고 쪄서 만드는 대표적인 찌는 떡에 해당합니다. 따라서 시루떡과 설기 모두 찌는 떡의 분류에 속합니다."
    },
    {
      "year": 2017,
      "number": 20,
      "text": "식물의 필수원소는 아니지만 벼의 경우 질소에 10배에 달하는 양을 흡수하여 이용한다. 벼에서 줄기 및 왕겨의 표피조직에 많은 성분은?",
      "choice_1": "나트륨",
      "choice_2": "셀레늄",
      "choice_3": "규소",
      "choice_4": "요오드",
      "answer": "3",
      "explanation": "벼의 필수원소는 아니지만, 벼는 다른 작물에 비해 규소(Si)를 매우 많이 흡수합니다. 규소는 벼의 줄기와 왕겨의 표피 조직에 축적되어 세포벽을 강화하고, 물리적인 지지력을 향상시키며, 병해충 저항성과 도복(쓰러짐) 저항성을 높여줍니다. 또한 증산작용을 조절하여 가뭄 스트레스에 대한 저항력을 증대시키는 역할을 합니다. 문제에서 언급된 '질소에 10배에 달하는 양을 흡수하여 이용'하며 '줄기 및 왕겨의 표피조직에 많은 성분'이라는 특징은 규소의 대표적인 기능과 일치합니다."
    },
    {
      "year": 2017,
      "number": 31,
      "text": "다음 중 10분도 쌀(백미)에 해당하는 것은?",
      "choice_1": "현미중량의 약 90%로 도정한 쌀",
      "choice_2": "현미중량의 약 93%로 도정한 쌀",
      "choice_3": "현미중량의 약 95%로 도정한 쌀",
      "choice_4": "현미중량의 약 97%로 도정한 쌀",
      "answer": "2",
      "explanation": "10분도 쌀은 백미를 의미하며, 이는 현미로부터 미강층과 쌀눈을 거의 완전히 제거한 상태의 쌀을 말합니다. 일반적으로 10분도 쌀은 현미 중량의 약 90% 내외로 도정된 것으로 보지만, 본 문제에서는 '현미중량의 약 93%로 도정한 쌀'을 10분도 쌀(백미)로 제시하고 있습니다. 이는 쌀의 외피가 충분히 제거되어 우리가 흔히 소비하는 백미의 형태가 된 것을 의미합니다."
    },
    {
      "year": 2017,
      "number": 32,
      "text": "다음 중 찹쌀에 대한 설명으로 바른 것은?",
      "choice_1": "녹말이 아밀로오스뿐이다.",
      "choice_2": "녹말이 아밀로펙틴뿐이다.",
      "choice_3": "녹말 중에 아밀로펙틴이 5 ~ 30%를 차지한다.",
      "choice_4": "녹말 중에 아밀로오스가 5 ~ 30%를 차지한다.",
      "answer": "2",
      "explanation": "찹쌀은 멥쌀과 달리 녹말을 구성하는 아밀로오스가 거의 없고 아밀로펙틴만으로 이루어져 있습니다. 아밀로펙틴은 가지가 많이 달린 구조를 가지며, 이로 인해 찹쌀은 찰지고 끈적이는 특성을 가지게 됩니다. 따라서 찹쌀의 녹말이 아밀로펙틴뿐이라는 설명이 바릅니다."
    },
    {
      "year": 2017,
      "number": 33,
      "text": "다음 중 술제조용으로 적합한 쌀은?",
      "choice_1": "소립종의 복백미",
      "choice_2": "대립종의 유백미",
      "choice_3": "소립종의 심백미",
      "choice_4": "대립종의 심백립",
      "answer": "4",
      "explanation": "술 제조용 쌀은 전분 함량이 높고 단백질과 지방 함량이 낮은 것이 중요하다. '심백(心白)'은 쌀알의 중심부에 전분질이 밀집되어 불투명하게 흰색을 띠는 부분으로, 심백이 크고 뚜렷할수록 효소에 의한 전분 분해가 용이하고 술의 맛을 좋게 한다. 또한 '대립종'은 쌀알이 커서 정미(精米) 과정에서 쌀을 깎아내더라도 심백 부분을 효율적으로 보존할 수 있어 양조에 유리하다. 따라서 대립종의 심백립이 술 제조용으로 가장 적합하다."
    },
    {
      "year": 2018,
      "number": 1,
      "text": "쌀에 대한 설명으로 바르지 못한 것은?",
      "choice_1": "쌀 생산량이 가장 많은 나라는 인도이다.",
      "choice_2": "세계 쌀의 90% 이상이 아시아에서 생산된다.",
      "choice_3": "약 1.5억 ha에서 매년 약 4.5억톤(현미)이 생산된다.",
      "choice_4": "FAO가 권장하는 쌀 재고율(60일간 소비할 량)은 16%이다.",
      "answer": "1",
      "explanation": "쌀 생산량이 가장 많은 나라는 중국이며, 인도는 중국 다음으로 두 번째로 많은 쌀을 생산합니다. 따라서 보기에 제시된 ①번 내용은 바르지 않습니다."
    },
    {
      "year": 2018,
      "number": 5,
      "text": "다음 쌀 성분 중 함량이 가장 높은 것은?",
      "choice_1": "탄수화물",
      "choice_2": "단백질",
      "choice_3": "지방",
      "choice_4": "섬유소",
      "answer": "1",
      "explanation": "쌀은 전 세계적으로 주식으로 소비되는 주요 곡물이며, 그 주된 역할은 에너지 공급원입니다. 쌀의 성분 중 가장 많은 비중을 차지하는 것은 탄수화물이며, 특히 전분 형태로 존재하여 쌀 중량의 75~80% 이상을 구성합니다. 따라서 함량이 가장 높은 성분은 탄수화물입니다."
    },
    {
      "year": 2018,
      "number": 8,
      "text": "현미에서 종피, 호분층, 배, 배유 중 무게비율이 가장 높은 것은?",
      "choice_1": "배",
      "choice_2": "배유",
      "choice_3": "종피",
      "choice_4": "호분층",
      "answer": "2",
      "explanation": "현미는 쌀의 왕겨만 벗겨낸 상태로, 쌀알의 주요 구성 성분은 배유, 배, 종피, 호분층입니다. 이 중 배유는 주로 탄수화물(전분)을 저장하는 부분으로, 쌀알 전체 무게의 약 90~93%를 차지하여 가장 큰 비중을 차지합니다. 따라서 무게 비율이 가장 높은 것은 배유입니다."
    },
    {
      "year": 2019,
      "number": 1,
      "text": "백미의 영양성분 함량이 올바른 것은?",
      "choice_1": "당질 71.8%",
      "choice_2": "단백질 6.8%",
      "choice_3": "지방 3.0%",
      "choice_4": "회분 1.3%",
      "answer": "2",
      "explanation": "백미의 주요 영양성분 함량은 당질 약 75~80%, 단백질 약 6.5~7.5%, 지방 약 0.5~0.7%, 회분 약 0.5~0.6% 정도로 알려져 있습니다. 따라서 단백질 함량 6.8%는 백미의 일반적인 영양성분 함량 범위에 해당합니다."
    },
    {
      "year": 2025,
      "number": 32,
      "text": "현미 깍은거",
      "choice_1": "-",
      "choice_2": "-",
      "choice_3": "-",
      "choice_4": "-",
      "answer": "0",
      "explanation": "백미"
    },
    {
      "year": 2025,
      "number": 47,
      "text": "쌀과 인슐린의 관계에 대한 설명으로 옳은 것은?",
      "choice_1": "-",
      "choice_2": "-",
      "choice_3": "-",
      "choice_4": "-",
      "answer": "0",
      "explanation": ""
    },
    {
      "year": 2025,
      "number": 59,
      "text": "진과 위과의 구분은?",
      "choice_1": "-",
      "choice_2": "-",
      "choice_3": "-",
      "choice_4": "-",
      "answer": "0",
      "explanation": ""
    },
    {
      "year": 2025,
      "number": 60,
      "text": "고추에 대한 설명은?",
      "choice_1": "-",
      "choice_2": "-",
      "choice_3": "-",
      "choice_4": "-",
      "answer": "0",
      "explanation": ""
    },
    {
      "year": 2025,
      "number": 73,
      "text": "현미를 벗기면 뭐가 되나?",
      "choice_1": "-",
      "choice_2": "-",
      "choice_3": "-",
      "choice_4": "-",
      "answer": "0",
      "explanation": "백미"
    },
    {
      "year": 2025,
      "number": 104,
      "text": "현미 깍은거",
      "choice_1": "-",
      "choice_2": "-",
      "choice_3": "-",
      "choice_4": "-",
      "answer": "0",
      "explanation": "백미"
    },
    {
      "year": 2025,
      "number": 119,
      "text": "쌀과 인슐린의 관계에 대한 설명으로 옳은 것은?",
      "choice_1": "-",
      "choice_2": "-",
      "choice_3": "-",
      "choice_4": "-",
      "answer": "0",
      "explanation": ""
    },
    {
      "year": 2025,
      "number": 131,
      "text": "진과 위과의 구분은?",
      "choice_1": "-",
      "choice_2": "-",
      "choice_3": "-",
      "choice_4": "-",
      "answer": "0",
      "explanation": ""
    },
    {
      "year": 2025,
      "number": 132,
      "text": "고추에 대한 설명은?",
      "choice_1": "-",
      "choice_2": "-",
      "choice_3": "-",
      "choice_4": "-",
      "answer": "0",
      "explanation": ""
    },
    {
      "year": 2025,
      "number": 145,
      "text": "현미를 벗기면 뭐가 되나?",
      "choice_1": "-",
      "choice_2": "-",
      "choice_3": "-",
      "choice_4": "-",
      "answer": "0",
      "explanation": "백미"
    }
  ]
}